LICENCE.md
MANIFEST.in
README.md
pyproject.toml
setup.py
neworder/__init__.py
neworder/__init__.pyi
neworder/df.pyi
neworder/domain.py
neworder/geospatial.py
neworder/mc.py
neworder/mpi.pyi
neworder/py.typed
neworder/stats.pyi
neworder/time.pyi
neworder.egg-info/PKG-INFO
neworder.egg-info/SOURCES.txt
neworder.egg-info/dependency_links.txt
neworder.egg-info/not-zip-safe
neworder.egg-info/requires.txt
neworder.egg-info/top_level.txt
src/ArrayHelpers.h
src/DataFrame.cpp
src/DataFrame.h
src/Helpers.h
src/Log.cpp
src/Log.h
src/Model.cpp
src/Model.h
src/Module.cpp
src/Module.h
src/Module_docstr.cpp
src/MonteCarlo.cpp
src/MonteCarlo.h
src/NPArray.cpp
src/NPArray.h
src/NewOrder.h
src/Timeline.cpp
src/Timeline.h
src/Timer.h