Metadata-Version: 2.4
Name: neworder
Version: 1.4.3
Summary: A dynamic microsimulation framework
Author-email: Andrew Smith <andrew@friarswood.net>
License: # MIT License
Project-URL: Homepage, https://neworder.readthedocs.io/
Project-URL: Bug Tracker, https://github.com/virgesmith/neworder/issues
Classifier: Programming Language :: Python :: 3.11
Classifier: Programming Language :: Python :: 3.12
Classifier: Programming Language :: Python :: 3.13
Classifier: License :: OSI Approved :: MIT License
Classifier: Operating System :: OS Independent
Requires-Python: >=3.10
License-File: LICENCE.md
Requires-Dist: pandas>=1.5.0
Requires-Dist: pandas-stubs
Requires-Dist: scipy>=1.9.3
Requires-Dist: matplotlib>=3.6.2
Provides-Extra: geospatial
Requires-Dist: networkx>3.0; extra == "geospatial"
Requires-Dist: osmnx>=2.0.0; extra == "geospatial"
Requires-Dist: geopandas>=0.12.2; extra == "geospatial"
Requires-Dist: shapely>=2.0.0; extra == "geospatial"
Provides-Extra: parallel
Requires-Dist: mpi4py>=3.0.3; extra == "parallel"
Dynamic: license-file
